newick_visualizer/__init__.py
newick_visualizer/_version.py
newick_visualizer/cli/__init__.py
newick_visualizer/cli/commands.py
newick_visualizer/core/__init__.py
newick_visualizer/core/template_manager.py
newick_visualizer/core/tree_generator.py
newick_visualizer/core/utils.py
newick_visualizer/templates/.DS_Store
newick_visualizer/templates/__init__.py
newick_visualizer/templates/base.html
newick_visualizer/templates/__pycache__/__init__.cpython-311.pyc
newick_visualizer/templates/__pycache__/__init__.cpython-313.pyc
newick_visualizer/templates/scripts/__init__.py
newick_visualizer/templates/scripts/groups.js
newick_visualizer/templates/scripts/layout.js
newick_visualizer/templates/scripts/main.js
newick_visualizer/templates/scripts/tree.js
newick_visualizer/templates/scripts/__pycache__/__init__.cpython-311.pyc
newick_visualizer/templates/scripts/__pycache__/__init__.cpython-313.pyc
newick_visualizer/templates/styles/__init__.py
newick_visualizer/templates/styles/main.css
newick_visualizer/templates/styles/__pycache__/__init__.cpython-311.pyc
newick_visualizer/templates/styles/__pycache__/__init__.cpython-313.pyc
newick_visualizer-1.1.1.dist-info/LICENSE
newick_visualizer-1.1.1.dist-info/METADATA
newick_visualizer-1.1.1.dist-info/WHEEL
newick_visualizer-1.1.1.dist-info/entry_points.txt
newick_visualizer-1.1.1.dist-info/top_level.txt
newick_visualizer-1.1.1.dist-info/RECORD
