Metadata-Version: 2.1
Name: newick-visualizer
Version: 1.1.1
Summary: A tool for visualizing Newick format phylogenetic trees
Home-page: https://github.com/Bengerthelorf/newick-visualizer
Author: Zane Loeng
Author-email: efd@live.com
Classifier: Development Status :: 5 - Production/Stable
Classifier: Intended Audience :: Science/Research
Classifier: Programming Language :: Python :: 3
Classifier: License :: OSI Approved :: MIT License
Classifier: Operating System :: OS Independent
Classifier: Topic :: Scientific/Engineering :: Bio-Informatics
Classifier: Topic :: Scientific/Engineering :: Visualization
Requires-Python: >=3.6
License-File: LICENSE
Requires-Dist: click >=8.0.0
Requires-Dist: selenium >=4.0.0
Requires-Dist: Pillow >=8.0.0
Requires-Dist: imgkit >=1.2.0
Requires-Dist: pdfkit >=1.0.0
